SPremiRNA/__init__.py
SPremiRNA/cell2loc.py
SPremiRNA/cor_analyze.py
SPremiRNA/malig_mirna.py
SPremiRNA/spatial_process.py
SPremiRNA/spatial_xgboost.py
SPremiRNA-0.1.dist-info/LICENSE
SPremiRNA-0.1.dist-info/METADATA
SPremiRNA-0.1.dist-info/WHEEL
SPremiRNA-0.1.dist-info/top_level.txt
SPremiRNA-0.1.dist-info/RECORD
