Metadata-Version: 2.1
Name: SPremiRNA
Version: 0.1
Summary: A simple example package
Home-page: http://github.com/yourusername/my_package
Author: Zero-plus-Seven
Author-email: linlinqi321@gmail.com
License: MIT
License-File: LICENSE
